TujieChanlunVol2/README.md
TujieChanlunVol2/__init__.py
TujieChanlunVol2/__main__.py
TujieChanlunVol2/file.epub
TujieChanlunVol2/index.html
TujieChanlunVol2/css/__init__.py
TujieChanlunVol2/css/annotations.css
TujieChanlunVol2/css/main.css
TujieChanlunVol2/css/normalize.css
TujieChanlunVol2/css/popup.css
TujieChanlunVol2/font/__init__.py
TujieChanlunVol2/font/fontello.eot
TujieChanlunVol2/font/fontello.svg
TujieChanlunVol2/font/fontello.ttf
TujieChanlunVol2/font/fontello.woff
TujieChanlunVol2/img/__init__.py
TujieChanlunVol2/img/annotator-glyph-sprite.png
TujieChanlunVol2/img/annotator-icon-sprite.png
TujieChanlunVol2/img/apple-touch-icon.png
TujieChanlunVol2/img/cancelfullscreen.png
TujieChanlunVol2/img/close.png
TujieChanlunVol2/img/fullscreen.png
TujieChanlunVol2/img/loader.gif
TujieChanlunVol2/img/menu-icon.png
TujieChanlunVol2/img/save.png
TujieChanlunVol2/img/saved.png
TujieChanlunVol2/img/settings-s.png
TujieChanlunVol2/img/settings.png
TujieChanlunVol2/img/star.png
TujieChanlunVol2/js/__init__.py
TujieChanlunVol2/js/epub.js
TujieChanlunVol2/js/epub.min.js
TujieChanlunVol2/js/epub.min.map
TujieChanlunVol2/js/hooks.min.js
TujieChanlunVol2/js/hooks.min.map
TujieChanlunVol2/js/reader.js
TujieChanlunVol2/js/reader.js.map
TujieChanlunVol2/js/reader.min.js
TujieChanlunVol2/js/reader.min.map
TujieChanlunVol2/js/hooks/__init__.py
TujieChanlunVol2/js/hooks/extensions/__init__.py
TujieChanlunVol2/js/hooks/extensions/highlight.js
TujieChanlunVol2/js/libs/__init__.py
TujieChanlunVol2/js/libs/jquery.min.js
TujieChanlunVol2/js/libs/localforage.min.js
TujieChanlunVol2/js/libs/screenfull.js
TujieChanlunVol2/js/libs/screenfull.min.js
TujieChanlunVol2/js/libs/zip.min.js
TujieChanlunVol2/js/plugins/__init__.py
TujieChanlunVol2/js/plugins/hypothesis.js
TujieChanlunVol2/js/plugins/search.js
tujie_chanlun_vol2-2022.10.15.0.dist-info/METADATA
tujie_chanlun_vol2-2022.10.15.0.dist-info/WHEEL
tujie_chanlun_vol2-2022.10.15.0.dist-info/entry_points.txt
tujie_chanlun_vol2-2022.10.15.0.dist-info/top_level.txt
tujie_chanlun_vol2-2022.10.15.0.dist-info/RECORD
